channel3_sdk/__init__.py
channel3_sdk/_base_client.py
channel3_sdk/_client.py
channel3_sdk/_compat.py
channel3_sdk/_constants.py
channel3_sdk/_exceptions.py
channel3_sdk/_files.py
channel3_sdk/_models.py
channel3_sdk/_qs.py
channel3_sdk/_resource.py
channel3_sdk/_response.py
channel3_sdk/_streaming.py
channel3_sdk/_types.py
channel3_sdk/_version.py
channel3_sdk/py.typed
channel3_sdk/_utils/__init__.py
channel3_sdk/_utils/_compat.py
channel3_sdk/_utils/_datetime_parse.py
channel3_sdk/_utils/_logs.py
channel3_sdk/_utils/_proxy.py
channel3_sdk/_utils/_reflection.py
channel3_sdk/_utils/_resources_proxy.py
channel3_sdk/_utils/_streams.py
channel3_sdk/_utils/_sync.py
channel3_sdk/_utils/_transform.py
channel3_sdk/_utils/_typing.py
channel3_sdk/_utils/_utils.py
channel3_sdk/lib/.keep
channel3_sdk/resources/__init__.py
channel3_sdk/resources/brands.py
channel3_sdk/resources/enrich.py
channel3_sdk/resources/price_tracking.py
channel3_sdk/resources/products.py
channel3_sdk/resources/search.py
channel3_sdk/resources/websites.py
channel3_sdk/types/__init__.py
channel3_sdk/types/availability_status.py
channel3_sdk/types/brand.py
channel3_sdk/types/brand_find_params.py
channel3_sdk/types/brand_list_params.py
channel3_sdk/types/enrich_enrich_url_params.py
channel3_sdk/types/paginated_list_brands_response.py
channel3_sdk/types/paginated_subscriptions.py
channel3_sdk/types/price.py
channel3_sdk/types/price_history.py
channel3_sdk/types/price_tracking_get_history_params.py
channel3_sdk/types/price_tracking_list_subscriptions_params.py
channel3_sdk/types/price_tracking_start_params.py
channel3_sdk/types/price_tracking_stop_params.py
channel3_sdk/types/product.py
channel3_sdk/types/product_detail.py
channel3_sdk/types/product_retrieve_params.py
channel3_sdk/types/redirect_mode.py
channel3_sdk/types/search_config_param.py
channel3_sdk/types/search_filter_price_param.py
channel3_sdk/types/search_filters_param.py
channel3_sdk/types/search_perform_params.py
channel3_sdk-2.12.0.dist-info/METADATA
channel3_sdk-2.12.0.dist-info/WHEEL
channel3_sdk-2.12.0.dist-info/licenses/LICENSE
channel3_sdk-2.12.0.dist-info/RECORD
